geometry_zyrenk/__init__.py
geometry_zyrenk/shapes2d.py
geometry_zyrenk/shapes3d.py
geometry_zyrenk/utils.py
geometry_zyrenk-1.0.0.dist-info/METADATA
geometry_zyrenk-1.0.0.dist-info/WHEEL
geometry_zyrenk-1.0.0.dist-info/top_level.txt
geometry_zyrenk-1.0.0.dist-info/RECORD
