Metadata-Version: 2.4
Name: geometry_zyrenk
Version: 1.0.0
Summary: مكتبة شاملة لحساب المساحة والمحيط للأشكال الثنائية والثلاثية الأبعاد
Author: Zyren_King
Classifier: Programming Language :: Python :: 3
Classifier: License :: OSI Approved :: MIT License
Classifier: Operating System :: OS Independent
Requires-Python: >=3.7
Dynamic: author
Dynamic: classifier
Dynamic: description
Dynamic: description-content-type
Dynamic: requires-python
Dynamic: summary
